Workbook

Sheet Resumo
A1: Alelo no e-commerce Jilo — pesquisa de provedores e custos
A2: Pesquisa pública feita em 29/09/2026. Valores da Alelo não são publicados: tratar como estimativa até receber proposta formal.
A4: Conclusões
A5: 1 | B5: Não existe app de pagamento na Shopify Brasil que aceite Alelo (nem outro vale-refeição). Qualquer caminho exige integração própria, no mesmo modelo já construído para a VR (cobrança fora do checkout + pedido criado na Shopify).
A6: 2 | B6: A única rota online documentada publicamente para Alelo é a Cielo (API E-commerce 3.0 ou Cielo Gateway/Braspag). A Alelo precisa habilitar o lojista antes. A Getnet (adquirente atual) aparece só para maquininha.
A7: 3 | B7: Ponto em aberto crítico: a Pagar.me informa que o contrato Cielo–Alelo terminou e bloqueia novas integrações. A documentação da Cielo segue ativa (atualizada em 2025/2026). Confirmar com Alelo e Cielo se aceitam cliente novo antes de orçar a integração.
A8: 4 | B8: A Alelo não publica tabela de taxas. O custo é negociado no credenciamento. Por isso a simulação usa 3 cenários: teto legal (3,6%), média Brasil 2026 (6,18%) e média SP 2026 (8,62%).
A9: 5 | B9: Regras do PAT (Decreto 12.712/2025) em vigor desde 10/02/2026: MDR máx. 3,6%, intercâmbio máx. 2%, repasse em até 15 dias corridos, proibidas tarifas extras. TRF-3 derrubou as liminares (24/02/2026) e o STF manteve o decreto (25/09/2026). Base legal para exigir 3,6% na negociação.
A10: 6 | B10: Interoperabilidade (qualquer cartão de benefício em qualquer credenciadora) prevista para ~07/11/2026. Se entrar em vigor, a Getnet ou outras podem passar a capturar Alelo online. Vale reavaliar em dez/2026 antes de investir numa integração só com a Cielo.
A12: Próximos passos recomendados
A13: 1 | B13: Ligar no credenciamento Alelo (4002-5011) e pedir proposta por escrito: MDR, prazo de repasse, tarifas, e quais credenciadoras capturam Alelo online hoje.
A14: 2 | B14: Confirmar com a Cielo se habilita Alelo e-commerce para novo cliente (API E-commerce 3.0 ou Gateway).
A15: 3 | B15: Perguntar à Getnet se terá Alelo e-commerce com a interoperabilidade do PAT.
A16: 4 | B16: Preencher as células amarelas da aba 'Premissas' com os valores reais da proposta. A aba 'Simulação por volume' recalcula sozinha.
A18: Como ler a planilha
A19: • | B19: Premissas: todas as taxas e o ticket médio. Texto azul com fundo amarelo = valor editável.
A20: • | B20: Simulação por volume: custo mensal e anual por faixa de faturamento em Alelo, nos 3 cenários, comparado com Pix e crédito.
A21: • | B21: Provedores: comparativo de quem aceita Alelo online. Regras PAT e Benchmarks: base regulatória e o que o mercado paga. Fontes: links consultados.

Sheet Premissas
A1: Premissas da simulação
A2: Células em azul com fundo amarelo são editáveis. Substituir pelos valores da proposta da Alelo/Cielo quando chegarem.
A4: Premissa | B4: Valor | C4: Origem / observação
A5: Ticket médio do pedido pago com Alelo (R$) | B5: 150 | C5: Estimativa. Pedido com 7 marmitas (frete grátis) sai perto de R$ 130–160. Ajustar pelo ticket real da Shopify.
A6: Cenário A — MDR Alelo (teto legal PAT) | B6: 0.036 | C6: Decreto 12.712/2025, art. 182-B, I. Melhor caso: exigir o teto na negociação.
A7: Cenário A — tarifa fixa Alelo por transação (R$) | B7: 0 | C7: Tarifas extras proibidas pelo art. 182-B.
A8: Cenário B — MDR Alelo (média Brasil 2026) | B8: 0.0618 | C8: Pesquisa Ipsos-Ipec/ANR, taxa média de vale-refeição, divulgada em 22/08/2026.
A9: Cenário B — tarifa fixa Alelo por transação (R$) | B9: 0 | C9: Sem tarifa fixa no cenário médio.
A10: Cenário C — MDR Alelo (média SP 2026) | B10: 0.0862 | C10: Mesma pesquisa, recorte São Paulo. Pior caso realista.
A11: Cenário C — tarifa fixa Alelo por transação (R$) | B11: 0.55 | C11: Tarifa relatada por lojistas no Reclame Aqui (pré-decreto, hoje vedada). Confiança baixa.
A12: Tarifa do gateway Cielo por transação (R$) | B12: 0 | C12: SOB CONSULTA — preencher com a proposta da Cielo. Zero até lá.
A13: Mensalidade do gateway Cielo (R$/mês) | B13: 0 | C13: SOB CONSULTA — preencher com a proposta da Cielo. Zero até lá.
A14: Comparativo — taxa média Pix 2026 | B14: 0.0106 | C14: Pesquisa Ipsos-Ipec/ANR 2026.
A15: Comparativo — taxa média débito 2026 | B15: 0.0177 | C15: Pesquisa Ipsos-Ipec/ANR 2026.
A16: Comparativo — taxa média crédito 2026 | B16: 0.0362 | C16: Pesquisa Ipsos-Ipec/ANR 2026.
A17: Prazo máximo de repasse Alelo (dias corridos) | B17: 15 | C17: Decreto 12.712/2025, art. 182-C. Antes do decreto: ~30 dias.

Sheet Simulação por volume
A1: Custo de aceitar Alelo por faixa de faturamento mensal
A2: Faturamento = valor vendido em Alelo no mês (não o faturamento total da loja). Custo = MDR × faturamento + tarifas fixas × nº de transações + mensalidade do gateway.
A4: Faturamento em Alelo / mês (R$) | B4: Nº de pedidos / mês | C4: Cenário A — custo/mês (teto 3,6%) | D4: A — % efetivo | E4: Cenário B — custo/mês (média BR) | F4: B — % efetivo | G4: Cenário C — custo/mês (média SP) | H4: C — % efetivo | I4: Se fosse Pix — custo/mês | J4: Se fosse crédito — custo/mês | K4: Custo extra Alelo vs Pix / mês (cenário B) | L4: Cenário A — custo/ano | M4: Cenário C — custo/ano | N4: Economia/ano negociando o teto (C − A)
A5: 2000 | B5: =IF(Premissas!$B$5>0,ROUND(A5/Premissas!$B$5,0),0) -> 13 | C5: =A5*Premissas!$B$6+B5*(Premissas!$B$7+Premissas!$B$12)+Premissas!$B$13 -> 72 | D5: =IF(A5>0,C5/A5,0) -> 0.036 | E5: =A5*Premissas!$B$8+B5*(Premissas!$B$9+Premissas!$B$12)+Premissas!$B$13 -> 123.6 | F5: =IF(A5>0,E5/A5,0) -> 0.0618 | G5: =A5*Premissas!$B$10+B5*(Premissas!$B$11+Premissas!$B$12)+Premissas!$B$13 -> 179.55 | H5: =IF(A5>0,G5/A5,0) -> 0.089775 | I5: =A5*Premissas!$B$14 -> 21.2 | J5: =A5*Premissas!$B$16 -> 72.4 | K5: =E5-I5 -> 102.4 | L5: =C5*12 -> 864 | M5: =G5*12 -> 2154.6 | N5: =M5-L5 -> 1290.6
A6: 5000 | B6: =IF(Premissas!$B$5>0,ROUND(A6/Premissas!$B$5,0),0) -> 33 | C6: =A6*Premissas!$B$6+B6*(Premissas!$B$7+Premissas!$B$12)+Premissas!$B$13 -> 180 | D6: =IF(A6>0,C6/A6,0) -> 0.036 | E6: =A6*Premissas!$B$8+B6*(Premissas!$B$9+Premissas!$B$12)+Premissas!$B$13 -> 309 | F6: =IF(A6>0,E6/A6,0) -> 0.0618 | G6: =A6*Premissas!$B$10+B6*(Premissas!$B$11+Premissas!$B$12)+Premissas!$B$13 -> 449.15 | H6: =IF(A6>0,G6/A6,0) -> 0.08983 | I6: =A6*Premissas!$B$14 -> 53 | J6: =A6*Premissas!$B$16 -> 181 | K6: =E6-I6 -> 256 | L6: =C6*12 -> 2160 | M6: =G6*12 -> 5389.8 | N6: =M6-L6 -> 3229.8
A7: 10000 | B7: =IF(Premissas!$B$5>0,ROUND(A7/Premissas!$B$5,0),0) -> 67 | C7: =A7*Premissas!$B$6+B7*(Premissas!$B$7+Premissas!$B$12)+Premissas!$B$13 -> 360 | D7: =IF(A7>0,C7/A7,0) -> 0.036 | E7: =A7*Premissas!$B$8+B7*(Premissas!$B$9+Premissas!$B$12)+Premissas!$B$13 -> 618 | F7: =IF(A7>0,E7/A7,0) -> 0.0618 | G7: =A7*Premissas!$B$10+B7*(Premissas!$B$11+Premissas!$B$12)+Premissas!$B$13 -> 898.85 | H7: =IF(A7>0,G7/A7,0) -> 0.089885 | I7: =A7*Premissas!$B$14 -> 106 | J7: =A7*Premissas!$B$16 -> 362 | K7: =E7-I7 -> 512 | L7: =C7*12 -> 4320 | M7: =G7*12 -> 10786.2 | N7: =M7-L7 -> 6466.2
A8: 20000 | B8: =IF(Premissas!$B$5>0,ROUND(A8/Premissas!$B$5,0),0) -> 133 | C8: =A8*Premissas!$B$6+B8*(Premissas!$B$7+Premissas!$B$12)+Premissas!$B$13 -> 720 | D8: =IF(A8>0,C8/A8,0) -> 0.036 | E8: =A8*Premissas!$B$8+B8*(Premissas!$B$9+Premissas!$B$12)+Premissas!$B$13 -> 1236 | F8: =IF(A8>0,E8/A8,0) -> 0.0618 | G8: =A8*Premissas!$B$10+B8*(Premissas!$B$11+Premissas!$B$12)+Premissas!$B$13 -> 1797.15 | H8: =IF(A8>0,G8/A8,0) -> 0.0898575 | I8: =A8*Premissas!$B$14 -> 212 | J8: =A8*Premissas!$B$16 -> 724 | K8: =E8-I8 -> 1024 | L8: =C8*12 -> 8640 | M8: =G8*12 -> 21565.8 | N8: =M8-L8 -> 12925.8
A9: 30000 | B9: =IF(Premissas!$B$5>0,ROUND(A9/Premissas!$B$5,0),0) -> 200 | C9: =A9*Premissas!$B$6+B9*(Premissas!$B$7+Premissas!$B$12)+Premissas!$B$13 -> 1080 | D9: =IF(A9>0,C9/A9,0) -> 0.036 | E9: =A9*Premissas!$B$8+B9*(Premissas!$B$9+Premissas!$B$12)+Premissas!$B$13 -> 1854 | F9: =IF(A9>0,E9/A9,0) -> 0.0618 | G9: =A9*Premissas!$B$10+B9*(Premissas!$B$11+Premissas!$B$12)+Premissas!$B$13 -> 2696 | H9: =IF(A9>0,G9/A9,0) -> 0.089866667 | I9: =A9*Premissas!$B$14 -> 318 | J9: =A9*Premissas!$B$16 -> 1086 | K9: =E9-I9 -> 1536 | L9: =C9*12 -> 12960 | M9: =G9*12 -> 32352 | N9: =M9-L9 -> 19392
A10: 50000 | B10: =IF(Premissas!$B$5>0,ROUND(A10/Premissas!$B$5,0),0) -> 333 | C10: =A10*Premissas!$B$6+B10*(Premissas!$B$7+Premissas!$B$12)+Premissas!$B$13 -> 1800 | D10: =IF(A10>0,C10/A10,0) -> 0.036 | E10: =A10*Premissas!$B$8+B10*(Premissas!$B$9+Premissas!$B$12)+Premissas!$B$13 -> 3090 | F10: =IF(A10>0,E10/A10,0) -> 0.0618 | G10: =A10*Premissas!$B$10+B10*(Premissas!$B$11+Premissas!$B$12)+Premissas!$B$13 -> 4493.15 | H10: =IF(A10>0,G10/A10,0) -> 0.089863 | I10: =A10*Premissas!$B$14 -> 530 | J10: =A10*Premissas!$B$16 -> 1810 | K10: =E10-I10 -> 2560 | L10: =C10*12 -> 21600 | M10: =G10*12 -> 53917.8 | N10: =M10-L10 -> 32317.8
A11: 75000 | B11: =IF(Premissas!$B$5>0,ROUND(A11/Premissas!$B$5,0),0) -> 500 | C11: =A11*Premissas!$B$6+B11*(Premissas!$B$7+Premissas!$B$12)+Premissas!$B$13 -> 2700 | D11: =IF(A11>0,C11/A11,0) -> 0.036 | E11: =A11*Premissas!$B$8+B11*(Premissas!$B$9+Premissas!$B$12)+Premissas!$B$13 -> 4635 | F11: =IF(A11>0,E11/A11,0) -> 0.0618 | G11: =A11*Premissas!$B$10+B11*(Premissas!$B$11+Premissas!$B$12)+Premissas!$B$13 -> 6740 | H11: =IF(A11>0,G11/A11,0) -> 0.089866667 | I11: =A11*Premissas!$B$14 -> 795 | J11: =A11*Premissas!$B$16 -> 2715 | K11: =E11-I11 -> 3840 | L11: =C11*12 -> 32400 | M11: =G11*12 -> 80880 | N11: =M11-L11 -> 48480
A12: 100000 | B12: =IF(Premissas!$B$5>0,ROUND(A12/Premissas!$B$5,0),0) -> 667 | C12: =A12*Premissas!$B$6+B12*(Premissas!$B$7+Premissas!$B$12)+Premissas!$B$13 -> 3600 | D12: =IF(A12>0,C12/A12,0) -> 0.036 | E12: =A12*Premissas!$B$8+B12*(Premissas!$B$9+Premissas!$B$12)+Premissas!$B$13 -> 6180 | F12: =IF(A12>0,E12/A12,0) -> 0.0618 | G12: =A12*Premissas!$B$10+B12*(Premissas!$B$11+Premissas!$B$12)+Premissas!$B$13 -> 8986.85 | H12: =IF(A12>0,G12/A12,0) -> 0.0898685 | I12: =A12*Premissas!$B$14 -> 1060 | J12: =A12*Premissas!$B$16 -> 3620 | K12: =E12-I12 -> 5120 | L12: =C12*12 -> 43200 | M12: =G12*12 -> 107842.2 | N12: =M12-L12 -> 64642.2
A13: 150000 | B13: =IF(Premissas!$B$5>0,ROUND(A13/Premissas!$B$5,0),0) -> 1000 | C13: =A13*Premissas!$B$6+B13*(Premissas!$B$7+Premissas!$B$12)+Premissas!$B$13 -> 5400 | D13: =IF(A13>0,C13/A13,0) -> 0.036 | E13: =A13*Premissas!$B$8+B13*(Premissas!$B$9+Premissas!$B$12)+Premissas!$B$13 -> 9270 | F13: =IF(A13>0,E13/A13,0) -> 0.0618 | G13: =A13*Premissas!$B$10+B13*(Premissas!$B$11+Premissas!$B$12)+Premissas!$B$13 -> 13480 | H13: =IF(A13>0,G13/A13,0) -> 0.089866667 | I13: =A13*Premissas!$B$14 -> 1590 | J13: =A13*Premissas!$B$16 -> 5430 | K13: =E13-I13 -> 7680 | L13: =C13*12 -> 64800 | M13: =G13*12 -> 161760 | N13: =M13-L13 -> 96960
A14: 200000 | B14: =IF(Premissas!$B$5>0,ROUND(A14/Premissas!$B$5,0),0) -> 1333 | C14: =A14*Premissas!$B$6+B14*(Premissas!$B$7+Premissas!$B$12)+Premissas!$B$13 -> 7200 | D14: =IF(A14>0,C14/A14,0) -> 0.036 | E14: =A14*Premissas!$B$8+B14*(Premissas!$B$9+Premissas!$B$12)+Premissas!$B$13 -> 12360 | F14: =IF(A14>0,E14/A14,0) -> 0.0618 | G14: =A14*Premissas!$B$10+B14*(Premissas!$B$11+Premissas!$B$12)+Premissas!$B$13 -> 17973.15 | H14: =IF(A14>0,G14/A14,0) -> 0.08986575 | I14: =A14*Premissas!$B$14 -> 2120 | J14: =A14*Premissas!$B$16 -> 7240 | K14: =E14-I14 -> 10240 | L14: =C14*12 -> 86400 | M14: =G14*12 -> 215677.8 | N14: =M14-L14 -> 129277.8
A16: Notas:
A17: • A coluna A (faixas) é editável: troque pelos volumes que o cliente espera.
A18: • Os cenários A/B/C puxam as taxas da aba 'Premissas'. Tarifa e mensalidade da Cielo estão zeradas até chegar a proposta (sob consulta).
A19: • Pequenos estabelecimentos (até R$ 30 mil/mês) pagaram em média 6,44% em 2026 (Ipsos-Ipec/ANR) — próximo do cenário B.
A20: • Não inclui o custo de desenvolvimento da integração (custom, fora do checkout Shopify, no mesmo molde da VR).
A21: • Com repasse em até 15 dias, não há custo de antecipação no modelo. Se a Jilo quiser receber antes, a taxa de antecipação da Alelo é sob consulta.

Sheet Provedores
A1: Comparativo de provedores — Alelo no e-commerce
A2: Status na data da pesquisa (29/09/2026). Verde = rota viável; amarelo = incerto; vermelho = não atende.
A4: Provedor | B4: Aceita Alelo online? | C4: Outros vales online | D4: MDR do vale | E4: Tarifa fixa / mensalidade | F4: Antifraude / 3DS | G4: Prazo de recebimento | H4: Integração com Shopify | I4: Esforço de integração | J4: Fonte | K4: Confiança
A5: Cielo — API E-commerce 3.0 | B5: Sim, documentado. Alelo enviado como débito (bandeira Elo, sem autenticação). Exige habilitação prévia pela Alelo e pela Cielo. | C5: Não documentado nesta API | D5: Negociado com a Alelo (teto legal 3,6%) | E5: Sob consulta | F5: Sem 3DS para Alelo | G5: Pela Alelo (máx. 15 dias) | H5: Não. O app Cielo na Shopify faz só cartão e Pix. Integração própria. | I5: Médio (parecido com a VR) | J5: docs.cielo.com.br/ecommerce-cielo/docs/alelo | K5: Média
A6: Cielo Gateway (Braspag / Pagador) | B6: Sim. Provedor 'Alelo': captura automática, sem pré-autorização, cancelamento só total. | C6: Ticket | D6: Negociado com cada bandeira | E6: Sob consulta | F6: Antifraude à parte, sob consulta | G6: Pela bandeira (máx. 15 dias) | H6: Não. Integração própria. | I6: Médio. Tem sandbox. | J6: docs.cielo.com.br/gateway/v1.0-en/reference/voucher-api | K6: Média-alta
A7: Pagar.me (Stone) | B7: Não. A documentação informa que, pelo fim do contrato Cielo–Alelo, não aceita novas integrações Alelo. | C7: VR, Pluxee (Sodexo), Ticket — só no plano Gateway | D7: Pela bandeira | E7: Sob consulta | F7: Antifraude integrado | G7: Pela bandeira | H7: O app Shopify faz só cartão, Pix e boleto. Vale exige integração própria. | I7: Médio | J7: docs.pagar.me/docs/voucher | K7: Alta
A8: Adyen | B8: Incerto. Marketing cita Alelo online, mas aviso de fev/2026 diz que online cobre só vale de arranjo aberto (Visa/Master/Elo). | C8: Vales de arranjo aberto (Caju, Flash, Swile etc.) | D8: Não publicado | E8: Preço global indicativo: US$ 0,13/transação + taxa. Costuma exigir volume mínimo. | F8: Incluído | G8: Sob consulta | H8: Integração própria | I8: Alto | J8: adyen.com/pricing; help.adyen.com (fev/2026) | K8: Baixa
A9: EBANX | B9: Documentação cita Alelo, Ticket, Sodexo e VR. Exige código de afiliação de cada bandeira. Foco em vendas internacionais. | C9: VR, Ticket, Sodexo | D9: Sob consulta | E9: Sob consulta | F9: Sob consulta | G9: Sob consulta | H9: Integração própria | I9: Médio-alto | J9: docs.ebanx.com | K9: Baixa
A10: Getnet (adquirente atual) | B10: Não encontrado para e-commerce. Aceita Alelo só na maquininha (desde 2016). | C10: — | D10: — | E10: — | F10: — | G10: — | H10: — | I10: — | J10: monitormercantil.com.br; buscas 29/09/2026 | K10: Média
A11: Rede, PagBank, Mercado Pago, Stone, Iugu, Vindi, Zoop, Appmax, Yampi | B11: Nenhuma evidência de Alelo online. PagBank, Mercado Pago e Stone aceitam vale só na maquininha. | C11: — | D11: — | E11: — | F11: — | G11: — | H11: Nenhum app Shopify com vale | I11: — | J11: Buscas 29/09/2026 | K11: Baixa (ausência de evidência)
A12: Alelo direto (sem gateway) | B12: Não há API pública de e-commerce da Alelo para lojista. Confirmar no credenciamento. | C12: — | D12: Sob consulta | E12: Sob consulta | F12: — | G12: Até 1 dia anunciado (com antecipação); lei: máx. 15 dias | H12: — | I12: — | J12: alelo.com.br/estabelecimentos/credenciamento | K12: Média
A13: Referência: VR (já integrada) | B13: Não se aplica — a Jilo já integra a VR direto (API Captura da VR). | C13: — | D13: Negociado com a VR (teto 3,6%) | E13: — | F13: — | G13: Máx. 15 dias | H13: Integração própria já feita (draft order) | I13: Feito | J13: Projeto Jilo | K13: Alta

Sheet Regras PAT
A1: Regras do PAT — Decreto 12.712/2025
A2: Publicado em 12/11/2025. Situação em 29/09/2026.
A4: Regra | B4: Valor / conteúdo | C4: Vigência | D4: Status em set/2026 | E4: Fonte
A5: Teto de MDR (taxa ao lojista) | B5: Máximo 3,6% | C5: Desde 10/02/2026 | D5: Em vigor | E5: Decreto, art. 182-B, I (camara.leg.br)
A6: Teto de intercâmbio | B6: Máximo 2% | C6: Desde 10/02/2026 | D6: Em vigor | E6: Decreto, art. 182-B, II
A7: Tarifas adicionais | B7: Proibidas (adesão, anuidade, tarifa por transação, TOR) | C7: Desde 10/02/2026 | D7: Em vigor — exigir por escrito na proposta | E7: Decreto, art. 182-B
A8: Prazo de repasse | B8: Até 15 dias corridos | C8: Desde 10/02/2026 | D8: Em vigor (antes: ~30 dias) | E8: Decreto, art. 182-C
A9: Deságio / rebate ao empregador | B9: Proibido | C9: Desde 10/02/2026 | D9: Em vigor | E9: Decreto, art. 182-F, I
A10: Arranjo aberto | B10: Obrigatório para operadoras com mais de 500 mil trabalhadores | C10: Desde 11/05/2026 | D10: Em litígio (liminar da Alelo derrubada pelo TRF-3; mérito pendente) | E10: comunidadecontabilbrasil.com; migalhas.com.br
A11: Interoperabilidade | B11: Qualquer cartão de benefício aceito em qualquer credenciadora | C11: ~07/11/2026 | D11: Ainda não vigente | E11: Decreto, art. 182-D, II
A12: Liminares das operadoras | B12: Ticket, VR, Pluxee e Alelo obtiveram liminares | C12: — | D12: Derrubadas pelo TRF-3 em 24/02/2026 | E12: bloomberglinea.com.br
A13: STF — ADI 7.962 | B13: Ação contra o decreto | C13: — | D13: Não conhecida (25/09/2026); decreto mantido; cabe agravo | E13: migalhas.com.br
A14: Alcance | B14: Vale para transações PAT. Há divergência se cobre todo vale-refeição/alimentação | C14: — | D14: Ponto a confirmar com a Alelo | E14: pluxee.com.br; amdjus.com.br

Sheet Benchmarks
A1: Quanto o mercado paga — benchmarks públicos
A2: Taxas por operadora (Alelo, VR, Ticket, Pluxee) não são publicadas; só médias de mercado.
A4: Indicador | B4: Valor | C4: Fonte | D4: Data | E4: Confiança
A5: Taxa média vale-refeição — Brasil 2026 | B5: 0.0618 | C5: Ipsos-Ipec/ANR via mercadoeconsumo.com.br | D5: 22/08/2026 | E5: Alta
A6: Taxa média vale-refeição — São Paulo 2026 | B6: 0.0862 | C6: Ipsos-Ipec/ANR via mercadoeconsumo.com.br | D6: 22/08/2026 | E6: Alta
A7: Taxa média vale-refeição — pequenos (até R$ 30 mil/mês) 2026 | B7: 0.0644 | C7: Ipsos-Ipec/ANR via mercadoeconsumo.com.br | D7: 22/08/2026 | E7: Alta
A8: Taxa média vale-refeição — Brasil 2025 | B8: 0.0519 | C8: Ipsos-Ipec/ANR via gironews.com | D8: 2025 | E8: Alta
A9: Pix — média 2026 | B9: 0.0106 | C9: Ipsos-Ipec/ANR | D9: 22/08/2026 | E9: Alta
A10: Débito — média 2026 | B10: 0.0177 | C10: Ipsos-Ipec/ANR | D10: 22/08/2026 | E10: Alta
A11: Crédito — média 2026 | B11: 0.0362 | C11: Ipsos-Ipec/ANR | D11: 22/08/2026 | E11: Alta
A12: Alelo relatada por lojistas (pré-decreto) | B12: 6,5% a 8,9% + R$ 0,55/transação + R$ 0,90/depósito | C12: Reclame Aqui (resumo de busca) | D12: n/d | E12: Baixa
A13: Faixa histórica de taxa de vale (pré-decreto) | B13: 6% a 13% | C13: gironews / resumo de busca | D13: 2025 | E13: Baixa
A14: Participação de vales no faturamento de restaurantes | B14: ~15% (até 80% em alguns) | C14: Abrasel via gironews.com | D14: 11/11/2025 | E14: Média

Sheet Elegibilidade
A1: Requisitos e restrições para a Jilo
A2: CNPJ 05.574.020/0001-90 (dados públicos da Receita via brasilapi.com.br).
A4: Item | B4: Achado | C4: Fonte | D4: Confiança
A5: CNAE principal | B5: 4712-1/00 (minimercado/mercearia) — tende a enquadrar no Alelo Alimentação. | C5: brasilapi.com.br (29/09/2026) | D5: Alta
A6: CNAEs secundários | B6: 5611-2/01 (restaurantes) e 5611-2/03 — habilitam o Alelo Refeição. | C6: brasilapi.com.br (29/09/2026) | D6: Alta
A7: Refeição x Alimentação | B7: Marmita congelada pode caber nos dois, conforme o CNAE/MCC aprovado. A decisão é da Alelo no credenciamento. | C7: pluxee.com.br (02/03/2026) | D7: Média
A8: Credenciamento | B8: Cadastro do CNPJ na Alelo (credenciamento.alelo.com.br ou 4002-5011). Aprovação em 3–10 dias úteis. Depois, o código de afiliação vai para a Cielo. | C8: Cielo docs; sindrio.com.br | D8: Alta
A9: Tipo de transação | B9: Débito, bandeira enviada como Elo, sem 3DS. O cliente informa número, nome, validade e CVV. | C9: docs.cielo.com.br (03/06/2026) | D9: Alta
A10: Cancelamento | B10: Sem pré-autorização e sem estorno parcial: só cancelamento total (impacta trocas/ajustes de pedido). | C10: Cielo Gateway docs (16/06/2026) | D10: Alta
A11: Checkout | B11: Checkout Shopify não aceita vale. Pagamento Alelo precisa rodar fora dele, como a VR. | C11: Pesquisa de apps Shopify | D11: Média
A12: Descontos do site | B12: Definir se o cupom PIX5 também vale para Alelo (como foi decidido para a VR). | C12: Decisão de negócio pendente | D12: —

Sheet Fontes
A1: Fontes consultadas
A2: Acessadas em 29/09/2026.
A4: Fonte | B4: Uso
A5: https://docs.cielo.com.br/ecommerce-cielo/docs/alelo | B5: Alelo na API E-commerce Cielo
A6: https://docs.cielo.com.br/gateway/v1.0-en/reference/voucher-api | B6: Alelo/Ticket no Cielo Gateway (Braspag)
A7: https://docs.pagar.me/docs/voucher | B7: Pagar.me: vales aceitos e bloqueio Alelo
A8: https://www.adyen.com/pricing | B8: Preço indicativo Adyen
A9: https://help.adyen.com/updates/introduction-of-changes-to-voucher-pat-program-integration-visa-mastercard | B9: Mudança PAT na Adyen (fev/2026)
A10: https://www.alelo.com.br/estabelecimentos/credenciamento | B10: Credenciamento Alelo
A11: https://www.camara.leg.br (texto do Decreto 12.712/2025) | B11: Regras do PAT
A12: https://www.bloomberglinea.com.br (24/02/2026) | B12: TRF-3 derruba liminares
A13: https://www.migalhas.com.br/quentes/449739 ; /depeso/465252 | B13: Liminar Alelo; STF ADI 7.962
A14: https://mercadoeconsumo.com.br (22/08/2026) | B14: Pesquisa Ipsos-Ipec/ANR 2026
A15: https://gironews.com | B15: Pesquisa 2025; participação dos vales
... A18: https://brasilapi.com.br/api/cnpj/v1/05574020000190 | B18: CNAEs da Jilo
